MANIFEST.in
README.txt
setup.cfg
setup.py
docs/HISTORY.txt
horae/__init__.py
horae.dashboard.egg-info/PKG-INFO
horae.dashboard.egg-info/SOURCES.txt
horae.dashboard.egg-info/dependency_links.txt
horae.dashboard.egg-info/entry_points.txt
horae.dashboard.egg-info/namespace_packages.txt
horae.dashboard.egg-info/not-zip-safe
horae.dashboard.egg-info/requires.txt
horae.dashboard.egg-info/top_level.txt
horae/dashboard/__init__.py
horae/dashboard/configure.zcml
horae/dashboard/dashboard.py
horae/dashboard/interfaces.py
horae/dashboard/latest.py
horae/dashboard/notification.py
horae/dashboard/reports.py
horae/dashboard/resource.py
horae/dashboard/resources.py
horae/dashboard/ticketing.py
horae/dashboard/traversal.py
horae/dashboard/viewlets.py
horae/dashboard/views.py
horae/dashboard/locales/horae.dashboard.pot
horae/dashboard/locales/de/LC_MESSAGES/horae.dashboard.mo
horae/dashboard/locales/de/LC_MESSAGES/horae.dashboard.po
horae/dashboard/static/dashboard.css
horae/dashboard/static/dashboard.js
horae/dashboard/static/notification.js
horae/dashboard/static/ticketing.js
horae/dashboard/templates/dashboard.cpt
horae/dashboard/viewlet_templates/dashboards.cpt
horae/dashboard/viewlet_templates/sidebar.cpt