Metadata-Version: 1.0
Name: horae.dashboard
Version: 1.0a1
Summary: Provides a dashboard for Horae
Home-page: UNKNOWN
Author: Simon Kaeser
Author-email: skaeser@gmail.com
License: GPL
Platform: UNKNOWN
Classifier: Programming Language :: Python
